pyceres.cpython-39-darwin.so
pyceres-2.6.dist-info/RECORD
pyceres-2.6.dist-info/WHEEL
pyceres-2.6.dist-info/METADATA
pyceres-2.6.dist-info/licenses/LICENSE
