Metadata-Version: 2.2
Name: pyceres
Version: 2.6
Summary: Factor graph optimization with Ceres, in Python
Author-Email: Paul-Edouard Sarlin <paul.edouard.sarlin@gmail.com>, Philipp Lindenberger <plindenbe@ethz.ch>, Shaohui Liu <b1ueber2y@gmail.com>
License: Apache-2.0
Classifier: License :: OSI Approved :: Apache Software License
Classifier: Programming Language :: Python :: 3 :: Only
Project-URL: Repository, https://github.com/cvg/pyceres
Requires-Python: >=3.9
Requires-Dist: numpy
